setup.py
sunnyday25/__init__.py
sunnyday25/sunnyday.py
sunnyday25.egg-info/PKG-INFO
sunnyday25.egg-info/SOURCES.txt
sunnyday25.egg-info/dependency_links.txt
sunnyday25.egg-info/requires.txt
sunnyday25.egg-info/top_level.txt